streamdeckfs/__init__.py
streamdeckfs/__main__.py
streamdeckfs/common.py
streamdeckfs/py_expression_eval.py
streamdeckfs/threads.py
streamdeckfs/web.py
streamdeckfs/assets/fonts/noto-emoji/LICENSE
streamdeckfs/assets/fonts/noto-emoji/NotoColorEmoji.ttf
streamdeckfs/assets/fonts/roboto/LICENSE.txt
streamdeckfs/assets/fonts/roboto/Roboto-Black.ttf
streamdeckfs/assets/fonts/roboto/Roboto-BlackItalic.ttf
streamdeckfs/assets/fonts/roboto/Roboto-Bold.ttf
streamdeckfs/assets/fonts/roboto/Roboto-BoldItalic.ttf
streamdeckfs/assets/fonts/roboto/Roboto-Italic.ttf
streamdeckfs/assets/fonts/roboto/Roboto-Light.ttf
streamdeckfs/assets/fonts/roboto/Roboto-LightItalic.ttf
streamdeckfs/assets/fonts/roboto/Roboto-Medium.ttf
streamdeckfs/assets/fonts/roboto/Roboto-MediumItalic.ttf
streamdeckfs/assets/fonts/roboto/Roboto-Regular.ttf
streamdeckfs/assets/fonts/roboto/Roboto-Thin.ttf
streamdeckfs/assets/fonts/roboto/Roboto-ThinItalic.ttf
streamdeckfs/assets/web/statics/common.css
streamdeckfs/assets/web/statics/common.js
streamdeckfs/assets/web/statics/jquery-3.6.0.min.js
streamdeckfs/assets/web/templates/auth.jinja2
streamdeckfs/assets/web/templates/deck.jinja2
streamdeckfs/assets/web/templates/index.jinja2
streamdeckfs/commands/__init__.py
streamdeckfs/commands/api.py
streamdeckfs/commands/base.py
streamdeckfs/commands/create_web_deck.py
streamdeckfs/commands/inspect.py
streamdeckfs/commands/make_dirs.py
streamdeckfs/commands/run.py
streamdeckfs/entities/__init__.py
streamdeckfs/entities/base.py
streamdeckfs/entities/deck.py
streamdeckfs/entities/event.py
streamdeckfs/entities/image.py
streamdeckfs/entities/key.py
streamdeckfs/entities/page.py
streamdeckfs/entities/text.py
streamdeckfs/entities/var.py
streamdeckfs/watchers/__init__.py
streamdeckfs/watchers/base.py
streamdeckfs/watchers/inotify.py
streamdeckfs-1.8.2.dist-info/LICENSE
streamdeckfs-1.8.2.dist-info/METADATA
streamdeckfs-1.8.2.dist-info/WHEEL
streamdeckfs-1.8.2.dist-info/entry_points.txt
streamdeckfs-1.8.2.dist-info/top_level.txt
streamdeckfs-1.8.2.dist-info/RECORD
