Metadata-Version: 2.1
Name: streamdeckfs
Version: 1.8.2
Summary: A software to handle a StreamDeck from Elgato, via the file system.
Home-page: https://github.com/twidi/streamdeckfs
Author: Stephane "Twidi" Angel
Author-email: s.angel@twidi.com
License: MIT
Keywords: streamdeck,elgato,inotify
Platform: Linux
Classifier: Development Status :: 5 - Production/Stable
Classifier: Intended Audience :: Developers
Classifier: License :: OSI Approved :: MIT License
Classifier: Operating System :: POSIX :: Linux
Classifier: Programming Language :: Python
Classifier: Programming Language :: Python :: 3
Classifier: Programming Language :: Python :: 3 :: Only
Classifier: Programming Language :: Python :: 3.9
Requires-Python: >=3.9
Requires-Dist: aiohttp
Requires-Dist: aiohttp-jinja2
Requires-Dist: cached-property
Requires-Dist: click
Requires-Dist: click-log
Requires-Dist: cloup
Requires-Dist: emoji
Requires-Dist: inotify-simple
Requires-Dist: jinja2
Requires-Dist: networkx
Requires-Dist: pillow
Requires-Dist: ProxyTypes
Requires-Dist: psutil
Requires-Dist: streamdeck
Provides-Extra: dev
Requires-Dist: black ; extra == 'dev'
Requires-Dist: flake8 ; extra == 'dev'
Requires-Dist: isort ; extra == 'dev'
Provides-Extra: thread-names
Requires-Dist: python-prctl ; extra == 'thread-names'
